{
    "world": {
        "name": "Мир Теней",
        "description": "Темный мир, населенный магическими существами и древними руинами.",
        "locations": [
            {
                "name": "Лесные руины",
                "description": "Древние лесные руины, покрытые мхом и лианами. Здесь обитают странные создания."
            },
            {
                "name": "Затерянный город",
                "description": "В глубине пустыни скрывается затерянный город, полный тайн и опасностей."
            },
            {
                "name": "Подземелье Теней",
                "description": "Темное подземелье с лабиринтами и монстрами. Здесь хранятся древние артефакты."
            },
            {
                "name": "Озеро Слез",
                "description": "Мистическое озеро, окруженное туманом. Легенды говорят, что здесь живут водяные духи."
            },
            {
                "name": "Горы Огня",
                "description": "Вулканические горы, где обитают драконы и другие огненные существа."
            },
            {
                "name": "Ледяная пустошь",
                "description": "Холодные равнины, покрытые снегом и льдом. Здесь живут белые медведи и снежные тролли."
            },
            {
                "name": "Пустыня Забвения",
                "description": "Бескрайняя пустыня, где время останавливается. Здесь полно заблудших душ и древних загадок."
            },
            {
                "name": "Темный лес",
                "description": "Густой и мрачный лес, полный опасностей. Здесь обитают волшебные существа и злые духи."
            },
            {
                "name": "Старый замок",
                "description": "Руины древнего замка, где когда-то правил могущественный король. Теперь здесь живут призраки."
            },
            {
                "name": "Остров Призраков",
                "description": "Таинственный остров, окруженный мистическими туманами. Здесь говорят о проклятиях и сокровищах."
            }
        ]
    },
    "characters": [
        {
            "name": "Гриша",
            "description": "Старый мудрец, очень нелюдим и неопрятен. У него огромная борода.",
            "dialogues": ["О, странник! Ты пришел в поисках знаний?", "Артефакт, о котором ты говоришь, хранит великую силу. Но будь осторожен, многие пытались его найти и не вернулись."],
            "quests": [
                "Найди потерянный артефакт в Лесных руинах.",
                "Исследуй Подземелье Теней и принеси мне древний ключ."
            ]
        },
        {
            "name": "Никитос",
            "description": "Дварф-кузнец, мастер своего дела. У него огромные запасы золота.",
            "dialogues": ["Приветствую тебя! Я кузнец Никитос. Чего ты желаешь?", "У меня есть лучшее оружие и доспехи. Что бы ты хотел купить?"],
            "quests": [
                "Найди редкую руду в Горах Огня.",
                "Принеси мне кусок метеорита из Ледяной пустоши.",
                "Помоги мне защитить мою казну от разбойников.",
                "Исследуй Подземелье Теней и принеси мне древний артефакт, чтобы укрепить мою казну."
            ]
        },
        {
            "name": "Даник",
            "description": "Человек, юный и наивный искатель приключений. Постоянно попадает в неприятные ситуации из который не может выбраться сам. Даник может добавляться в процессе выполнения квеста. Например, игрок может встретить Даника в Лесных руинах, который будет плакать и просить ему помочь.",
            "dialogues": ["Привет! Я Даник, я очень сильный и умный, но тут такая задачка, ну вообще невозможная. У меня почему-то не получается", "Ой, я опять заблудился... Поможешь мне найти дорогу домой?"],
            "quests": [
                "Найди потерянную Даником кирассу в Лесных руинах.",
                "Спасти его из клетки бандитов около Затерянного города."
            ]
        },
        {
            "name": "Макс",
            "description": "Огр, глупый даже по меркам Огров. Его выгнали из племени за глупость. Настолько глупый, что ему тяжело говорить. Постоянно бьёт себя дубинов по голове и врезается в стены. Макс может быть случайно найден игроком и предложить дополнительные задачи по ходу основного квеста.",
            "dialogues": ["Привет! Я Макс, огр. У меня есть большая дубина!", "Ой, я забыл, куда иду... Поможешь мне?"],
            "quests": [
                "Ударь Макса по голове его же дубиной.",
                "Облей Макса водой из Озера Слез.",
                "Побегай кругами вокруг Макса."
            ]
        }
    ]
}